{
  "fields": [
    { "db_field": "client_name", "pdf_field": "NOME" },
    { "db_field": "weapon_id", "pdf_field": "ID_ARMA" },
    { "db_field": "body_measurements_open_palm1", "pdf_field": "mao_aberta_1" },
    { "db_field": "body_measurements_open_palm2", "pdf_field": "mao_aberta_2" },
    { "db_field": "body_measurements_open_palm3", "pdf_field": "mao_aberta_3" },
    { "db_field": "body_measurements_open_palm4", "pdf_field": "mao_aberta_4" },
    { "db_field": "body_measurements_open_palm5", "pdf_field": "mao_aberta_5" },
    { "db_field": "body_measurements_open_palm6", "pdf_field": "mao_aberta_6" },
    { "db_field": "body_measurements_body1", "pdf_field": "corpo_1" },
    { "db_field": "body_measurements_body2", "pdf_field": "corpo_2" },
    { "db_field": "body_measurements_body3", "pdf_field": "corpo_3" },
    { "db_field": "body_measurements_weight", "pdf_field": "peso" },
    { "db_field": "body_measurements_age", "pdf_field": "idade" },
    { "db_field": "body_measurements_hand_in_position1", "pdf_field": "mao_posicao_1" },
    { "db_field": "body_measurements_hand_in_position2", "pdf_field": "mao_posicao_2" },
    { "db_field": "body_measurements_hand_in_position3", "pdf_field": "mao_posicao_3" },
    { "db_field": "body_measurements_between_hands", "pdf_field": "entre_maos" }
  ]
}